{
  "name": "Benjamin Guerrero",
  "age": 63,
  "address": {
    "street": "Kaflut Mill",
    "city": "Cabokcoc",
    "state": "MS",
    "zip": "93927"
  },
  "contact": {
    "phone": "(706) 815-8167",
    "servicePhone": "800137847"
  },
  "birthday": "1959-06-21T03:32:16.981Z",
  "ip": "13.164.106.54",
  "foo": "bar",
  "profile": {
    "about": "Amuunro ko uzozoj oj zic bacuho se pe zukozdac ga jup dibzusru pocwu bagoken kidisvaj dumdebha afnatfiw. Necwe bo ku fovasvu vamop me lilum wobol vul poofwi edegonsi jabawir lipeg pe gorfibeh teusa relali. Gapar vac uhonekuf cev nanzajnoz rekawoazi opi ufetogij honoswiv vir abfezub seabepo feut awo rege mothepid. Du peha ceis bucpef ulzo dosi cofde eloase suk owuni for uce ti mo. Si mu juorbon faj sob wu ced jefi tav watwa vam sicwam pijzur vilot cujbugruk unulole ejluk lahco.",
    "bio": "Mopjakis awow relohan epkuw nezoav ovmi jiwronwo lusfen pe corcu ab bimaki difidgom. Fif mesjej indon wil nah dafkoujo rasicat hi wa ziru wav tosbuusi rorholget. Ukajeunu ajfu ba rerpiw boaba gijbace fumom nil usag epemihheg wal heg. Ca oruti uwava pefik dupdej lolvod we uc loze ofumekoso oj pem so ki ru pipovi mum opozviz."
  },
  "apiKey": "0eacd46af3ec479f85e294d4479fa0820b6ffe060db9e965e3a26ce8483936d6",
  "currency": {
    "code": "JMD",
    "name": "Jamaica Dollar"
  }
}