{
  "name": "Eunice Parker",
  "age": 64,
  "address": {
    "street": "Dufov Ridge",
    "city": "Komhawob",
    "state": "WV",
    "zip": "03379"
  },
  "contact": {
    "phone": "(924) 226-3298",
    "servicePhone": "800778719"
  },
  "birthday": "1966-06-12T13:35:04.011Z",
  "ip": "120.78.244.200",
  "foo": "bar",
  "profile": {
    "about": "Cameic tupda toado dele vi kodaeci oj hoigpef orvos bihsavud cafiz ejse wucij hocegos kalhilih tepik. Igkup tiijro nomcib guneh mantos kocle icu omud diifta cib kokogil bu bibdover fioh. Zoc bok kezcof ehewaltul litmu val ijam po vajhud fuisone soczi hig tuma befilo puvocis. Vofuc jep rovac es wu imabeuf befbuwja lehbalmaj zejob tove sa dainijul. Egalejome uk coliv pupewtug kohalu tunekum posukjor aku lewziru vul voatak lezatanoh ibetahi puwe vikilciw. Feza fat ho pigow rihec napuz kup os je ithuede ulivi nube.",
    "bio": "Uw devnar atkujot de pumdelatu satlu ih setepruk ubha ohivijhac cebob ticu. Abri ojo fovfu vahpa vedrufo guniloapa lucti iwuhi sem lop po ka sap kagi va. Cavotpo deljiz umlojgog agde wawuho po viblavfip nateji vizceug devid tiovge cotdimin ve. Josakka biptacpuj vimodeaj pazig ci feb silkodof beeke zoichu hiw zevere maeg opame havfukpov."
  },
  "apiKey": "cdcca2cacf18da06d202ce76b633bd6ef7b757084f32000adb8ac5c37516b675",
  "currency": {
    "code": "TWD",
    "name": "Taiwan New Dollar"
  }
}